cpubuilder/__init__.py
cpubuilder/binary_helper.py
cpubuilder/debug_tools.py
cpubuilder/instruction_builder.py
cpubuilder/memory_helper.py
cpubuilder-0.1.0.dist-info/licenses/LICENSE
cpubuilder-0.1.0.dist-info/METADATA
cpubuilder-0.1.0.dist-info/WHEEL
cpubuilder-0.1.0.dist-info/top_level.txt
cpubuilder-0.1.0.dist-info/RECORD
