Metadata-Version: 2.4
Name: cpubuilder
Version: 0.1.0
Summary: A library for building CPU emulators in Python
Home-page: https://github.com/FlandollScarlet495/cpubuilder
Author: Yukino Kotone
Author-email: YukinoKotone <nakamurakensuke5@gmail.com>
License: MIT
Project-URL: Homepage, https://github.com/FlandollScarlet495/cpubuilder
Project-URL: Repository, https://github.com/FlandollScarlet495/cpubuilder.git
Classifier: Development Status :: 3 - Alpha
Classifier: Intended Audience :: Developers
Classifier: License :: OSI Approved :: MIT License
Classifier: Operating System :: OS Independent
Classifier: Programming Language :: Python :: 3
Classifier: Programming Language :: Python :: 3.7
Classifier: Programming Language :: Python :: 3.8
Classifier: Programming Language :: Python :: 3.9
Classifier: Programming Language :: Python :: 3.10
Classifier: Programming Language :: Python :: 3.11
Classifier: Topic :: Software Development :: Libraries :: Python Modules
Classifier: Topic :: Software Development :: Embedded Systems
Requires-Python: >=3.7
License-File: LICENSE
Dynamic: author
Dynamic: home-page
Dynamic: license-file
Dynamic: requires-python
